shredderscales/__init__.py
shredderscales/__main__.py
shredderscales/notes.py
shredderscales/scales.py
shredderscales/shredder.py
shredderscales/tests/__init__.py
shredderscales/tests/test_scales.py
shredderscales/tests/test_shredder.py
shredderscales-1.0.5.dist-info/licenses/LICENSE
shredderscales-1.0.5.dist-info/METADATA
shredderscales-1.0.5.dist-info/WHEEL
shredderscales-1.0.5.dist-info/entry_points.txt
shredderscales-1.0.5.dist-info/top_level.txt
shredderscales-1.0.5.dist-info/RECORD
