Metadata-Version: 2.4
Name: shredderscales
Version: 1.0.5
Summary: Guitar-scales for any key and tuning
Home-page: https://github.com/jrw24/shredder-scales
Author: Jamie Wangen
License-File: LICENSE
Requires-Dist: matplotlib>=3.10
Requires-Dist: mpld3
Dynamic: author
Dynamic: description
Dynamic: description-content-type
Dynamic: home-page
Dynamic: license-file
Dynamic: requires-dist
Dynamic: summary
